einvoice_lens/__init__.py
einvoice_lens/cli.py
einvoice_lens/engine.py
einvoice_lens-0.1.3.dist-info/METADATA
einvoice_lens-0.1.3.dist-info/WHEEL
einvoice_lens-0.1.3.dist-info/licenses/LICENSE
einvoice_lens-0.1.3.dist-info/RECORD
