Metadata-Version: 2.4
Name: einvoice-lens
Version: 0.1.3
Summary: Einvoice Lens is a package that uses OCR and rule-based parsing to transform Vietnam's electronic invoices into structured data
Project-URL: Documentation, https://github.com/thuyetbao/einvoice-lens#README
Project-URL: Issues, https://github.com/thuyetbao/einvoice-lens/issues
Project-URL: Source, https://github.com/thuyetbao/einvoice-lens
Author-email: Thuyet Bao <trthuyetbao@gmail.com>
License-Expression: MIT
License-File: LICENSE
Keywords: ocr,python3,rule-based-parsing,vietnam-electronic-invoices
Classifier: Development Status :: 5 - Production/Stable
Classifier: Operating System :: OS Independent
Classifier: Programming Language :: Python
Classifier: Programming Language :: Python :: 3
Classifier: Programming Language :: Python :: 3.12
Classifier: Programming Language :: Python :: 3.13
Requires-Python: >=3.12
Requires-Dist: google-crc32c<2.0,>=1.7.1
Requires-Dist: pdfplumber<0.12,>=0.11.5
Requires-Dist: polars<1.35,>=1.7.1
